setup.py
feed2tweet/__init__.py
feed2tweet/addtags.py
feed2tweet/cliparse.py
feed2tweet/confparse.py
feed2tweet/feedcache.py
feed2tweet/filterentry.py
feed2tweet/main.py
feed2tweet/removeduplicates.py
feed2tweet/tweetpost.py
feed2tweet.egg-info/PKG-INFO
feed2tweet.egg-info/SOURCES.txt
feed2tweet.egg-info/dependency_links.txt
feed2tweet.egg-info/requires.txt
feed2tweet.egg-info/top_level.txt
feed2tweet/plugins/__init__.py
feed2tweet/plugins/influxdbplugin.py
scripts/feed2tweet