Metadata-Version: 1.1
Name: feed2tweet
Version: 1.1
Summary: Parse rss feed and tweet new posts to Twitter
Home-page: https://github.com/chaica/feed2tweet
Author: Carl Chenet
Author-email: chaica@ohmytux.com
License: GNU GPL v3
Download-URL: https://github.com/chaica/feed2tweet
Platform: UNKNOWN
Classifier: Intended Audience :: End Users/Desktop
Classifier: Environment :: Console
Classifier: License :: OSI Approved :: GNU General Public License (GPL)
Classifier: Operating System :: POSIX :: Linux
Classifier: Programming Language :: Python :: 3.4
Classifier: Programming Language :: Python :: 3.5
Classifier: Programming Language :: Python :: 3.6
